Workbook

Sheet Dashbord
C1: WinPower Ltd
C3: Winpower Bangladesh is a company that provides high-quality products like batteries, shoes, and sunglasses. We focus on customer satisfaction, innovation, and environmental responsibility.

Sheet Raw data
A1: Billing_date | B1: Invoice_id | C1: Customer_id | D1: Customer_name | E1: Customer_type | F1: Sales_zone | G1: Sales_id | H1: Sales_person | I1: Product_code | J1: Product_name | K1: Battery_type | L1: Quantity | M1: Unit_price_pcs | N1: Amount | O1: Discount_percent | P1: Discount_amount | Q1: VAT_amount | R1: Sales_amount | S1: Payment_status | T1: Payment_method | U1: Region_manager | V1: Delivery_date | W1: Due_date | X1: Return_status | Y1: notes
A2: 46018 | B2: INV-10000 | C2: CUST-1002 | D2: Karim Battery House | E2: Retail | F2: Patuyakhali | G2: S-108 | H2: Khairul Hasan | I2: BT1022 | J2: Power Bank Battery | K2: Lithium | L2: 10 | M2: 1764 | N2: 17640 | O2: 0 | P2: 0 | Q2: 882 | R2: 18522 | S2: Paid | T2: Nagad | U2: Shamim Ahmed | V2: 46020 | W2: 46041 | X2: Not Returned | Y2: Let close defense.
A3: 46097 | B3: INV-10001 | C3: CUST-1013 | D3: Sadia Enterprise | E3: Distributor | F3: Barisal | G3: S-106 | H3: Jahid Hasan | I3: BT1013 | J3: Nickel Cadmium Battery | K3: NiCd | L3: 4 | M3: 146 | N3: 584 | O3: 0 | P3: 0 | Q3: 29.2 | R3: 613.2 | S3: Paid | T3: bKash | U3: Nasir Uddin Ahmad | V3: 46101 | W3: 46120 | X3: Not Returned | Y3: Soldier gas behind school part seek.
A4: 45934 | B4: INV-10002 | C4: CUST-1032 | D4: Rangpur Power House | E4: Dealer | F4: Sylhet | G4: S-103 | H4: Sabbir Hossain | I4: BT1009 | J4: Automotive Battery | K4: Automotive | L4: 22 | M4: 1815 | N4: 39930 | O4: 5 | P4: 1996.5 | Q4: 1896.675 | R4: 39830.175 | S4: Paid | T4: Nagad | U4: Mahmud Hasan | V4: 45938 | W4: 45951 | X4: Not Returned | Y4: Outside general drug yet.
A5: 45978 | B5: INV-10003 | C5: CUST-1017 | D5: Hasan & Brothers | E5: Dealer | F5: Rangpur | G5: S-107 | H5: Rakibul Hasan | I5: BT1016 | J5: Forklift Battery | K5: Industrial | L5: 3 | M5: 1702 | N5: 5106 | O5: 0 | P5: 0 | Q5: 255.3 | R5: 5361.3 | S5: Paid | T5: Bank Transfer | U5: Mahmud Hasan | V5: 45980 | W5: 45992 | X5: Not Returned | Y5: Improve store gas start media financial.
A6: 46142 | B6: INV-10004 | C6: CUST-1005 | D6: Dhaka Battery Point | E6: Distributor | F6: Pabna | G6: S-109 | H6: Ruhul Amin | I6: BT1004 | J6: Gel Battery | K6: Gel | L6: 13 | M6: 607 | N6: 7891 | O6: 0 | P6: 0 | Q6: 394.55 | R6: 8285.55 | S6: Due | T6: Bank Transfer | U6: Yousuf Mazumder Anik | V6: 46143 | W6: 46167 | X6: Not Returned | Y6: Professor network soldier star leader.
A7: 45901 | B7: INV-10005 | C7: CUST-1001 | D7: Rahim Enterprise | E7: Dealer | F7: Barisal | G7: S-106 | H7: Jahid Hasan | I7: BT1007 | J7: Deep Cycle Battery | K7: Deep Cycle | L7: 28 | M7: 1140 | N7: 31920 | O7: 10 | P7: 3192 | Q7: 1436.4 | R7: 30164.4 | S7: Paid | T7: bKash | U7: Rafiqul Islam | V7: 45905 | W7: 45918 | X7: Not Returned | Y7: Treat evidence across affect bit main media clear.
A8: 45971 | B8: INV-10006 | C8: CUST-1021 | D8: Green Power BD | E8: Dealer | F8: Bogura | G8: S-113 | H8: Shamim Bepari | I8: BT1028 | J8: Start Stop Car Battery | K8: Automotive | L8: 30 | M8: 1103 | N8: 33090 | O8: 5 | P8: 1654.5 | Q8: 1571.775 | R8: 33007.275 | S8: Paid | T8: Cash | U8: Mahmud Hasan | V8: 45976 | W8: 45978 | X8: Not Returned | Y8: Serve onto treatment.
A9: 46128 | B9: INV-10007 | C9: CUST-1001 | D9: Rahim Enterprise | E9: Distributor | F9: Rajshahi | G9: S-105 | H9: Tanvir Rahman | I9: BT1003 | J9: AGM Battery | K9: AGM | L9: 27 | M9: 614 | N9: 16578 | O9: 2 | P9: 331.56 | Q9: 812.322 | R9: 17058.762 | S9: Partial | T9: Bank Transfer | U9: Hasanuzzaman Helal | V9: 46130 | W9: 46135 | X9: Not Returned | Y9: Management charge movement pattern present organization.
A10: 46013 | B10: INV-10008 | C10: CUST-1052 | D10: Anando Electronics Point | E10: Distributor | F10: Dhaka | G10: S-101 | H10: Rahim Ahmed | I10: BT1004 | J10: Gel Battery | K10: Gel | L10: 22 | M10: 1958 | N10: 43076 | O10: 5 | P10: 2153.8 | Q10: 2046.11 | R10: 42968.31 | S10: Paid | T10: Bank Transfer | U10: Mynuddin Hasan | V10: 46016 | W10: 46028 | X10: Not Returned | Y10: Federal bring even girl thousand type.
A11: 45970 | B11: INV-10009 | C11: CUST-1059 | D11: Sultan Power Solution | E11: Dealer | F11: Rangpur | G11: S-107 | H11: Rakibul Hasan | I11: BT1008 | J11: Motorcycle Battery | K11: Motorcycle | L11: 13 | M11: 637 | N11: 8281 | O11: 10 | P11: 828.1 | Q11: 372.645 | R11: 7825.545 | S11: Paid | T11: Nagad | U11: Shamim Ahmed | V11: 45973 | W11: 45998 | X11: Not Returned | Y11: Art significant bag even affect require.
A12: 46112 | B12: INV-10010 | C12: CUST-1029 | D12: Noakhali Enterprise | E12: Corporate | F12: Dhaka | G12: S-101 | H12: Rahim Ahmed | I12: BT1009 | J12: Automotive Battery | K12: Automotive | L12: 22 | M12: 652 | N12: 14344 | O12: 5 | P12: 717.2 | Q12: 681.34 | R12: 14308.14 | S12: Paid | T12: Bank Transfer | U12: Mahmud Hasan | V12: 46116 | W12: 46134 | X12: Not Returned | Y12: Country thus subject forget interest soldier.
A13: 45840 | B13: INV-10011 | C13: CUST-1051 | D13: Future Energy BD | E13: Retail | F13: Pabna | G13: S-109 | H13: Ruhul Amin | I13: BT1031 | J13: Coin Cell Battery | K13: Alkaline | L13: 21 | M13: 67 | N13: 1407 | O13: 0 | P13: 0 | Q13: 70.35 | R13: 1477.35 | S13: Paid | T13: Cash | U13: Yousuf Mazumder Anik | V13: 45844 | W13: 45861 | X13: Not Returned | Y13: Guy value point begin care must factor movement.
... A5001: 45831 | B5001: INV-14999 | C5001: CUST-1015 | D5001: Sumi Battery House | E5001: Retail | F5001: Mymensingh | G5001: S-112 | H5001: Shahriar Joy | I5001: BT1013 | J5001: Nickel Cadmium Battery | K5001: NiCd | L5001: 27 | M5001: 321 | N5001: 8667 | O5001: 0 | P5001: 0 | Q5001: 433.35 | R5001: 9100.35 | S5001: Partial | T5001: Cash | U5001: Nasir Uddin Ahmad | V5001: 45833 | W5001: 45849 | X5001: Returned | Y5001: Suffer never audience outside sense.

Sheet executive
B1: Sales_id | C1: Executive name | D1: Zone | E1: Region_manager
B2: S-101 | C2: {=XLOOKUP(B2,'Raw data'!G2:G5001,'Raw data'!H2:H5001)} -> #NAME? | D2: {=XLOOKUP(C2,'Raw data'!H2:H5001,'Raw data'!F2:F5001)} -> #NAME? | E2: {=XLOOKUP(D2,'Raw data'!F2:F5001,'Raw data'!U2:U5001)} -> #NAME?
B3: S-102 | C3: {=XLOOKUP(B3,'Raw data'!G3:G5002,'Raw data'!H3:H5002)} -> #NAME? | D3: {=XLOOKUP(C3,'Raw data'!H3:H5002,'Raw data'!F3:F5002)} -> #NAME? | E3: {=XLOOKUP(D3,'Raw data'!F3:F5002,'Raw data'!U3:U5002)} -> #NAME?
B4: S-103 | C4: {=XLOOKUP(B4,'Raw data'!G4:G5003,'Raw data'!H4:H5003)} -> #NAME? | D4: {=XLOOKUP(C4,'Raw data'!H4:H5003,'Raw data'!F4:F5003)} -> #NAME? | E4: {=XLOOKUP(D4,'Raw data'!F4:F5003,'Raw data'!U4:U5003)} -> #NAME?
B5: S-104 | C5: {=XLOOKUP(B5,'Raw data'!G5:G5004,'Raw data'!H5:H5004)} -> #NAME? | D5: {=XLOOKUP(C5,'Raw data'!H5:H5004,'Raw data'!F5:F5004)} -> #NAME? | E5: {=XLOOKUP(D5,'Raw data'!F5:F5004,'Raw data'!U5:U5004)} -> #NAME?
B6: S-105 | C6: {=XLOOKUP(B6,'Raw data'!G6:G5005,'Raw data'!H6:H5005)} -> #NAME? | D6: {=XLOOKUP(C6,'Raw data'!H6:H5005,'Raw data'!F6:F5005)} -> #NAME? | E6: {=XLOOKUP(D6,'Raw data'!F6:F5005,'Raw data'!U6:U5005)} -> #NAME?
B7: S-106 | C7: {=XLOOKUP(B7,'Raw data'!G7:G5006,'Raw data'!H7:H5006)} -> #NAME? | D7: {=XLOOKUP(C7,'Raw data'!H7:H5006,'Raw data'!F7:F5006)} -> #NAME? | E7: {=XLOOKUP(D7,'Raw data'!F7:F5006,'Raw data'!U7:U5006)} -> #NAME?
B8: S-107 | C8: {=XLOOKUP(B8,'Raw data'!G8:G5007,'Raw data'!H8:H5007)} -> #NAME? | D8: {=XLOOKUP(C8,'Raw data'!H8:H5007,'Raw data'!F8:F5007)} -> #NAME? | E8: {=XLOOKUP(D8,'Raw data'!F8:F5007,'Raw data'!U8:U5007)} -> #NAME?
B9: S-108 | C9: {=XLOOKUP(B9,'Raw data'!G9:G5008,'Raw data'!H9:H5008)} -> #NAME? | D9: {=XLOOKUP(C9,'Raw data'!H9:H5008,'Raw data'!F9:F5008)} -> #NAME? | E9: {=XLOOKUP(D9,'Raw data'!F9:F5008,'Raw data'!U9:U5008)} -> #NAME?
B10: S-109 | C10: {=XLOOKUP(B10,'Raw data'!G10:G5009,'Raw data'!H10:H5009)} -> #NAME? | D10: {=XLOOKUP(C10,'Raw data'!H10:H5009,'Raw data'!F10:F5009)} -> #NAME? | E10: {=XLOOKUP(D10,'Raw data'!F10:F5009,'Raw data'!U10:U5009)} -> #NAME?
B11: S-110 | C11: {=XLOOKUP(B11,'Raw data'!G11:G5010,'Raw data'!H11:H5010)} -> #NAME? | D11: {=XLOOKUP(C11,'Raw data'!H11:H5010,'Raw data'!F11:F5010)} -> #NAME? | E11: {=XLOOKUP(D11,'Raw data'!F11:F5010,'Raw data'!U11:U5010)} -> #NAME?

Sheet Product
A1: Product Code | B1: Product Name | C1: Product Type | D1: Unit Price
A2: BT1001 | B2: {=XLOOKUP(A2,'Raw data'!I2:I5001,'Raw data'!J2:J5001)} -> #NAME? | C2: {=XLOOKUP(B2,'Raw data'!J2:J5001,'Raw data'!K2:K5001)} -> #NAME? | D2: {=XLOOKUP(B2,'Raw data'!J2:J5001,'Raw data'!M2:M5001)} -> #NAME?
A3: BT1002 | B3: {=XLOOKUP(A3,'Raw data'!I3:I5002,'Raw data'!J3:J5002)} -> #NAME? | C3: {=XLOOKUP(B3,'Raw data'!J3:J5002,'Raw data'!K3:K5002)} -> #NAME? | D3: {=XLOOKUP(B3,'Raw data'!J3:J5002,'Raw data'!M3:M5002)} -> #NAME?
A4: BT1003 | B4: {=XLOOKUP(A4,'Raw data'!I4:I5003,'Raw data'!J4:J5003)} -> #NAME? | C4: {=XLOOKUP(B4,'Raw data'!J4:J5003,'Raw data'!K4:K5003)} -> #NAME? | D4: {=XLOOKUP(B4,'Raw data'!J4:J5003,'Raw data'!M4:M5003)} -> #NAME?
A5: BT1004 | B5: {=XLOOKUP(A5,'Raw data'!I5:I5004,'Raw data'!J5:J5004)} -> #NAME? | C5: {=XLOOKUP(B5,'Raw data'!J5:J5004,'Raw data'!K5:K5004)} -> #NAME? | D5: {=XLOOKUP(B5,'Raw data'!J5:J5004,'Raw data'!M5:M5004)} -> #NAME?
A6: BT1005 | B6: {=XLOOKUP(A6,'Raw data'!I6:I5005,'Raw data'!J6:J5005)} -> #NAME? | C6: {=XLOOKUP(B6,'Raw data'!J6:J5005,'Raw data'!K6:K5005)} -> #NAME? | D6: {=XLOOKUP(B6,'Raw data'!J6:J5005,'Raw data'!M6:M5005)} -> #NAME?
A7: BT1006 | B7: {=XLOOKUP(A7,'Raw data'!I7:I5006,'Raw data'!J7:J5006)} -> #NAME? | C7: {=XLOOKUP(B7,'Raw data'!J7:J5006,'Raw data'!K7:K5006)} -> #NAME? | D7: {=XLOOKUP(B7,'Raw data'!J7:J5006,'Raw data'!M7:M5006)} -> #NAME?
A8: BT1007 | B8: {=XLOOKUP(A8,'Raw data'!I8:I5007,'Raw data'!J8:J5007)} -> #NAME? | C8: {=XLOOKUP(B8,'Raw data'!J8:J5007,'Raw data'!K8:K5007)} -> #NAME? | D8: {=XLOOKUP(B8,'Raw data'!J8:J5007,'Raw data'!M8:M5007)} -> #NAME?
A9: BT1008 | B9: {=XLOOKUP(A9,'Raw data'!I9:I5008,'Raw data'!J9:J5008)} -> #NAME? | C9: {=XLOOKUP(B9,'Raw data'!J9:J5008,'Raw data'!K9:K5008)} -> #NAME? | D9: {=XLOOKUP(B9,'Raw data'!J9:J5008,'Raw data'!M9:M5008)} -> #NAME?
A10: BT1009 | B10: {=XLOOKUP(A10,'Raw data'!I10:I5009,'Raw data'!J10:J5009)} -> #NAME? | C10: {=XLOOKUP(B10,'Raw data'!J10:J5009,'Raw data'!K10:K5009)} -> #NAME? | D10: {=XLOOKUP(B10,'Raw data'!J10:J5009,'Raw data'!M10:M5009)} -> #NAME?
A11: BT1010 | B11: {=XLOOKUP(A11,'Raw data'!I11:I5010,'Raw data'!J11:J5010)} -> #NAME? | C11: {=XLOOKUP(B11,'Raw data'!J11:J5010,'Raw data'!K11:K5010)} -> #NAME? | D11: {=XLOOKUP(B11,'Raw data'!J11:J5010,'Raw data'!M11:M5010)} -> #NAME?
A12: BT1011 | B12: {=XLOOKUP(A12,'Raw data'!I12:I5011,'Raw data'!J12:J5011)} -> #NAME? | C12: {=XLOOKUP(B12,'Raw data'!J12:J5011,'Raw data'!K12:K5011)} -> #NAME? | D12: {=XLOOKUP(B12,'Raw data'!J12:J5011,'Raw data'!M12:M5011)} -> #NAME?
A13: BT1012 | B13: {=XLOOKUP(A13,'Raw data'!I13:I5012,'Raw data'!J13:J5012)} -> #NAME? | C13: {=XLOOKUP(B13,'Raw data'!J13:J5012,'Raw data'!K13:K5012)} -> #NAME? | D13: {=XLOOKUP(B13,'Raw data'!J13:J5012,'Raw data'!M13:M5012)} -> #NAME?
... A29: BT1028 | B29: {=XLOOKUP(A29,'Raw data'!I29:I5028,'Raw data'!J29:J5028)} -> #NAME? | C29: {=XLOOKUP(B29,'Raw data'!J29:J5028,'Raw data'!K29:K5028)} -> #NAME? | D29: {=XLOOKUP(B29,'Raw data'!J29:J5028,'Raw data'!M29:M5028)} -> #NAME?
A30: BT1030 | B30: {=XLOOKUP(A30,'Raw data'!I31:I5030,'Raw data'!J31:J5030)} -> #NAME? | C30: {=XLOOKUP(B30,'Raw data'!J30:J5029,'Raw data'!K30:K5029)} -> #NAME? | D30: {=XLOOKUP(B30,'Raw data'!J30:J5029,'Raw data'!M30:M5029)} -> #NAME?
A31: BT1031 | B31: {=XLOOKUP(A31,'Raw data'!I32:I5031,'Raw data'!J32:J5031)} -> #NAME? | C31: {=XLOOKUP(B31,'Raw data'!J31:J5030,'Raw data'!K31:K5030)} -> #NAME? | D31: {=XLOOKUP(B31,'Raw data'!J31:J5030,'Raw data'!M31:M5030)} -> #NAME?

Sheet Customer
A1: Customer ID | B1: Customer Name | C1: Customer Zone | D1: Customer Type | E1: Assign Executive | F1: Regional Manager
A2: CUST-1001 | B2: {=XLOOKUP(A2,'Raw data'!C2:C5001,'Raw data'!D2:D5001)} -> #NAME? | C2: {=XLOOKUP(B2,'Raw data'!D2:D5001,'Raw data'!F2:F5001)} -> #NAME? | D2: {=XLOOKUP(B2,'Raw data'!D2:D5001,'Raw data'!E2:E5001)} -> #NAME? | E2: {=XLOOKUP(B2,'Raw data'!D2:D5001,'Raw data'!H2:H5001)} -> #NAME? | F2: {=XLOOKUP(B2,'Raw data'!D2:D5001,'Raw data'!U2:U5001)} -> #NAME?
A3: CUST-1002 | B3: {=XLOOKUP(A3,'Raw data'!C3:C5002,'Raw data'!D3:D5002)} -> #NAME? | C3: {=XLOOKUP(B3,'Raw data'!D3:D5002,'Raw data'!F3:F5002)} -> #NAME? | D3: {=XLOOKUP(B3,'Raw data'!D3:D5002,'Raw data'!E3:E5002)} -> #NAME? | E3: {=XLOOKUP(B3,'Raw data'!D3:D5002,'Raw data'!H3:H5002)} -> #NAME? | F3: {=XLOOKUP(B3,'Raw data'!D3:D5002,'Raw data'!U3:U5002)} -> #NAME?
A4: CUST-1003 | B4: {=XLOOKUP(A4,'Raw data'!C4:C5003,'Raw data'!D4:D5003)} -> #NAME? | C4: {=XLOOKUP(B4,'Raw data'!D4:D5003,'Raw data'!F4:F5003)} -> #NAME? | D4: {=XLOOKUP(B4,'Raw data'!D4:D5003,'Raw data'!E4:E5003)} -> #NAME? | E4: {=XLOOKUP(B4,'Raw data'!D4:D5003,'Raw data'!H4:H5003)} -> #NAME? | F4: {=XLOOKUP(B4,'Raw data'!D4:D5003,'Raw data'!U4:U5003)} -> #NAME?
A5: CUST-1004 | B5: {=XLOOKUP(A5,'Raw data'!C5:C5004,'Raw data'!D5:D5004)} -> #NAME? | C5: {=XLOOKUP(B5,'Raw data'!D5:D5004,'Raw data'!F5:F5004)} -> #NAME? | D5: {=XLOOKUP(B5,'Raw data'!D5:D5004,'Raw data'!E5:E5004)} -> #NAME? | E5: {=XLOOKUP(B5,'Raw data'!D5:D5004,'Raw data'!H5:H5004)} -> #NAME? | F5: {=XLOOKUP(B5,'Raw data'!D5:D5004,'Raw data'!U5:U5004)} -> #NAME?
A6: CUST-1005 | B6: {=XLOOKUP(A6,'Raw data'!C6:C5005,'Raw data'!D6:D5005)} -> #NAME? | C6: {=XLOOKUP(B6,'Raw data'!D6:D5005,'Raw data'!F6:F5005)} -> #NAME? | D6: {=XLOOKUP(B6,'Raw data'!D6:D5005,'Raw data'!E6:E5005)} -> #NAME? | E6: {=XLOOKUP(B6,'Raw data'!D6:D5005,'Raw data'!H6:H5005)} -> #NAME? | F6: {=XLOOKUP(B6,'Raw data'!D6:D5005,'Raw data'!U6:U5005)} -> #NAME?
A7: CUST-1006 | B7: {=XLOOKUP(A7,'Raw data'!C7:C5006,'Raw data'!D7:D5006)} -> #NAME? | C7: {=XLOOKUP(B7,'Raw data'!D7:D5006,'Raw data'!F7:F5006)} -> #NAME? | D7: {=XLOOKUP(B7,'Raw data'!D7:D5006,'Raw data'!E7:E5006)} -> #NAME? | E7: {=XLOOKUP(B7,'Raw data'!D7:D5006,'Raw data'!H7:H5006)} -> #NAME? | F7: {=XLOOKUP(B7,'Raw data'!D7:D5006,'Raw data'!U7:U5006)} -> #NAME?
A8: CUST-1007 | B8: {=XLOOKUP(A8,'Raw data'!C8:C5007,'Raw data'!D8:D5007)} -> #NAME? | C8: {=XLOOKUP(B8,'Raw data'!D8:D5007,'Raw data'!F8:F5007)} -> #NAME? | D8: {=XLOOKUP(B8,'Raw data'!D8:D5007,'Raw data'!E8:E5007)} -> #NAME? | E8: {=XLOOKUP(B8,'Raw data'!D8:D5007,'Raw data'!H8:H5007)} -> #NAME? | F8: {=XLOOKUP(B8,'Raw data'!D8:D5007,'Raw data'!U8:U5007)} -> #NAME?
A9: CUST-1008 | B9: {=XLOOKUP(A9,'Raw data'!C9:C5008,'Raw data'!D9:D5008)} -> #NAME? | C9: {=XLOOKUP(B9,'Raw data'!D9:D5008,'Raw data'!F9:F5008)} -> #NAME? | D9: {=XLOOKUP(B9,'Raw data'!D9:D5008,'Raw data'!E9:E5008)} -> #NAME? | E9: {=XLOOKUP(B9,'Raw data'!D9:D5008,'Raw data'!H9:H5008)} -> #NAME? | F9: {=XLOOKUP(B9,'Raw data'!D9:D5008,'Raw data'!U9:U5008)} -> #NAME?
A10: CUST-1009 | B10: {=XLOOKUP(A10,'Raw data'!C10:C5009,'Raw data'!D10:D5009)} -> #NAME? | C10: {=XLOOKUP(B10,'Raw data'!D10:D5009,'Raw data'!F10:F5009)} -> #NAME? | D10: {=XLOOKUP(B10,'Raw data'!D10:D5009,'Raw data'!E10:E5009)} -> #NAME? | E10: {=XLOOKUP(B10,'Raw data'!D10:D5009,'Raw data'!H10:H5009)} -> #NAME? | F10: {=XLOOKUP(B10,'Raw data'!D10:D5009,'Raw data'!U10:U5009)} -> #NAME?
A11: CUST-1010 | B11: {=XLOOKUP(A11,'Raw data'!C11:C5010,'Raw data'!D11:D5010)} -> #NAME? | C11: {=XLOOKUP(B11,'Raw data'!D11:D5010,'Raw data'!F11:F5010)} -> #NAME? | D11: {=XLOOKUP(B11,'Raw data'!D11:D5010,'Raw data'!E11:E5010)} -> #NAME? | E11: {=XLOOKUP(B11,'Raw data'!D11:D5010,'Raw data'!H11:H5010)} -> #NAME? | F11: {=XLOOKUP(B11,'Raw data'!D11:D5010,'Raw data'!U11:U5010)} -> #NAME?
A12: CUST-1011 | B12: {=XLOOKUP(A12,'Raw data'!C12:C5011,'Raw data'!D12:D5011)} -> #NAME? | C12: {=XLOOKUP(B12,'Raw data'!D12:D5011,'Raw data'!F12:F5011)} -> #NAME? | D12: {=XLOOKUP(B12,'Raw data'!D12:D5011,'Raw data'!E12:E5011)} -> #NAME? | E12: {=XLOOKUP(B12,'Raw data'!D12:D5011,'Raw data'!H12:H5011)} -> #NAME? | F12: {=XLOOKUP(B12,'Raw data'!D12:D5011,'Raw data'!U12:U5011)} -> #NAME?
A13: CUST-1012 | B13: {=XLOOKUP(A13,'Raw data'!C13:C5012,'Raw data'!D13:D5012)} -> #NAME? | C13: {=XLOOKUP(B13,'Raw data'!D13:D5012,'Raw data'!F13:F5012)} -> #NAME? | D13: {=XLOOKUP(B13,'Raw data'!D13:D5012,'Raw data'!E13:E5012)} -> #NAME? | E13: {=XLOOKUP(B13,'Raw data'!D13:D5012,'Raw data'!H13:H5012)} -> #NAME? | F13: {=XLOOKUP(B13,'Raw data'!D13:D5012,'Raw data'!U13:U5012)} -> #NAME?
... A46: CUST-1045 | B46: {=XLOOKUP(A46,'Raw data'!C46:C5045,'Raw data'!D46:D5045)} -> #NAME? | C46: {=XLOOKUP(B46,'Raw data'!D46:D5045,'Raw data'!F46:F5045)} -> #NAME? | D46: {=XLOOKUP(B46,'Raw data'!D46:D5045,'Raw data'!E46:E5045)} -> #NAME? | E46: {=XLOOKUP(B46,'Raw data'!D46:D5045,'Raw data'!H46:H5045)} -> #NAME? | F46: {=XLOOKUP(B46,'Raw data'!D46:D5045,'Raw data'!U46:U5045)} -> #NAME?
A47: CUST-1047 | B47: {=XLOOKUP(A47,'Raw data'!C48:C5047,'Raw data'!D48:D5047)} -> #NAME? | C47: {=XLOOKUP(B47,'Raw data'!D48:D5047,'Raw data'!F48:F5047)} -> #NAME? | D47: {=XLOOKUP(B47,'Raw data'!D48:D5047,'Raw data'!E48:E5047)} -> #NAME? | E47: {=XLOOKUP(B47,'Raw data'!D48:D5047,'Raw data'!H48:H5047)} -> #NAME? | F47: {=XLOOKUP(B47,'Raw data'!D48:D5047,'Raw data'!U48:U5047)} -> #NAME?
A48: CUST-1048 | B48: {=XLOOKUP(A48,'Raw data'!C49:C5048,'Raw data'!D49:D5048)} -> #NAME? | C48: {=XLOOKUP(B48,'Raw data'!D49:D5048,'Raw data'!F49:F5048)} -> #NAME? | D48: {=XLOOKUP(B48,'Raw data'!D49:D5048,'Raw data'!E49:E5048)} -> #NAME? | E48: {=XLOOKUP(B48,'Raw data'!D49:D5048,'Raw data'!H49:H5048)} -> #NAME? | F48: {=XLOOKUP(B48,'Raw data'!D49:D5048,'Raw data'!U49:U5048)} -> #NAME?
A49: CUST-1049 | B49: {=XLOOKUP(A49,'Raw data'!C50:C5049,'Raw data'!D50:D5049)} -> #NAME? | C49: {=XLOOKUP(B49,'Raw data'!D50:D5049,'Raw data'!F50:F5049)} -> #NAME? | D49: {=XLOOKUP(B49,'Raw data'!D50:D5049,'Raw data'!E50:E5049)} -> #NAME? | E49: {=XLOOKUP(B49,'Raw data'!D50:D5049,'Raw data'!H50:H5049)} -> #NAME? | F49: {=XLOOKUP(B49,'Raw data'!D50:D5049,'Raw data'!U50:U5049)} -> #NAME?
A50: CUST-1050 | B50: {=XLOOKUP(A50,'Raw data'!C51:C5050,'Raw data'!D51:D5050)} -> #NAME? | C50: {=XLOOKUP(B50,'Raw data'!D51:D5050,'Raw data'!F51:F5050)} -> #NAME? | D50: {=XLOOKUP(B50,'Raw data'!D51:D5050,'Raw data'!E51:E5050)} -> #NAME? | E50: {=XLOOKUP(B50,'Raw data'!D51:D5050,'Raw data'!H51:H5050)} -> #NAME? | F50: {=XLOOKUP(B50,'Raw data'!D51:D5050,'Raw data'!U51:U5050)} -> #NAME?
A51: CUST-1051 | B51: {=XLOOKUP(A51,'Raw data'!C52:C5051,'Raw data'!D52:D5051)} -> #NAME? | C51: {=XLOOKUP(B51,'Raw data'!D52:D5051,'Raw data'!F52:F5051)} -> #NAME? | D51: {=XLOOKUP(B51,'Raw data'!D52:D5051,'Raw data'!E52:E5051)} -> #NAME? | E51: {=XLOOKUP(B51,'Raw data'!D52:D5051,'Raw data'!H52:H5051)} -> #NAME? | F51: {=XLOOKUP(B51,'Raw data'!D52:D5051,'Raw data'!U52:U5051)} -> #NAME?
A52: CUST-1052 | B52: {=XLOOKUP(A52,'Raw data'!C53:C5052,'Raw data'!D53:D5052)} -> #NAME? | C52: {=XLOOKUP(B52,'Raw data'!D53:D5052,'Raw data'!F53:F5052)} -> #NAME? | D52: {=XLOOKUP(B52,'Raw data'!D53:D5052,'Raw data'!E53:E5052)} -> #NAME? | E52: {=XLOOKUP(B52,'Raw data'!D53:D5052,'Raw data'!H53:H5052)} -> #NAME? | F52: {=XLOOKUP(B52,'Raw data'!D53:D5052,'Raw data'!U53:U5052)} -> #NAME?
A53: CUST-1053 | B53: {=XLOOKUP(A53,'Raw data'!C54:C5053,'Raw data'!D54:D5053)} -> #NAME? | C53: {=XLOOKUP(B53,'Raw data'!D54:D5053,'Raw data'!F54:F5053)} -> #NAME? | D53: {=XLOOKUP(B53,'Raw data'!D54:D5053,'Raw data'!E54:E5053)} -> #NAME? | E53: {=XLOOKUP(B53,'Raw data'!D54:D5053,'Raw data'!H54:H5053)} -> #NAME? | F53: {=XLOOKUP(B53,'Raw data'!D54:D5053,'Raw data'!U54:U5053)} -> #NAME?
A54: CUST-1054 | B54: {=XLOOKUP(A54,'Raw data'!C55:C5054,'Raw data'!D55:D5054)} -> #NAME? | C54: {=XLOOKUP(B54,'Raw data'!D55:D5054,'Raw data'!F55:F5054)} -> #NAME? | D54: {=XLOOKUP(B54,'Raw data'!D55:D5054,'Raw data'!E55:E5054)} -> #NAME? | E54: {=XLOOKUP(B54,'Raw data'!D55:D5054,'Raw data'!H55:H5054)} -> #NAME? | F54: {=XLOOKUP(B54,'Raw data'!D55:D5054,'Raw data'!U55:U5054)} -> #NAME?
A55: CUST-1055 | B55: {=XLOOKUP(A55,'Raw data'!C56:C5055,'Raw data'!D56:D5055)} -> #NAME? | C55: {=XLOOKUP(B55,'Raw data'!D56:D5055,'Raw data'!F56:F5055)} -> #NAME? | D55: {=XLOOKUP(B55,'Raw data'!D56:D5055,'Raw data'!E56:E5055)} -> #NAME? | E55: {=XLOOKUP(B55,'Raw data'!D56:D5055,'Raw data'!H56:H5055)} -> #NAME? | F55: {=XLOOKUP(B55,'Raw data'!D56:D5055,'Raw data'!U56:U5055)} -> #NAME?
A56: CUST-1056 | B56: {=XLOOKUP(A56,'Raw data'!C57:C5056,'Raw data'!D57:D5056)} -> #NAME? | C56: {=XLOOKUP(B56,'Raw data'!D57:D5056,'Raw data'!F57:F5056)} -> #NAME? | D56: {=XLOOKUP(B56,'Raw data'!D57:D5056,'Raw data'!E57:E5056)} -> #NAME? | E56: {=XLOOKUP(B56,'Raw data'!D57:D5056,'Raw data'!H57:H5056)} -> #NAME? | F56: {=XLOOKUP(B56,'Raw data'!D57:D5056,'Raw data'!U57:U5056)} -> #NAME?
A57: CUST-1057 | B57: {=XLOOKUP(A57,'Raw data'!C58:C5057,'Raw data'!D58:D5057)} -> #NAME? | C57: {=XLOOKUP(B57,'Raw data'!D58:D5057,'Raw data'!F58:F5057)} -> #NAME? | D57: {=XLOOKUP(B57,'Raw data'!D58:D5057,'Raw data'!E58:E5057)} -> #NAME? | E57: {=XLOOKUP(B57,'Raw data'!D58:D5057,'Raw data'!H58:H5057)} -> #NAME? | F57: {=XLOOKUP(B57,'Raw data'!D58:D5057,'Raw data'!U58:U5057)} -> #NAME?
A58: CUST-1058 | B58: {=XLOOKUP(A58,'Raw data'!C59:C5058,'Raw data'!D59:D5058)} -> #NAME? | C58: {=XLOOKUP(B58,'Raw data'!D59:D5058,'Raw data'!F59:F5058)} -> #NAME? | D58: {=XLOOKUP(B58,'Raw data'!D59:D5058,'Raw data'!E59:E5058)} -> #NAME? | E58: {=XLOOKUP(B58,'Raw data'!D59:D5058,'Raw data'!H59:H5058)} -> #NAME? | F58: {=XLOOKUP(B58,'Raw data'!D59:D5058,'Raw data'!U59:U5058)} -> #NAME?
... A60: CUST-1060 | B60: {=XLOOKUP(A60,'Raw data'!C61:C5060,'Raw data'!D61:D5060)} -> #NAME? | C60: {=XLOOKUP(B60,'Raw data'!D61:D5060,'Raw data'!F61:F5060)} -> #NAME? | D60: {=XLOOKUP(B60,'Raw data'!D61:D5060,'Raw data'!E61:E5060)} -> #NAME? | E60: {=XLOOKUP(B60,'Raw data'!D61:D5060,'Raw data'!H61:H5060)} -> #NAME? | F60: {=XLOOKUP(B60,'Raw data'!D61:D5060,'Raw data'!U61:U5060)} -> #NAME?

Sheet Pivot Table Customer
A3: Row Labels | B3: Sum of Sales_amount
A4: Amin Battery Center | B4: 4982892.6
A5: Anando Electronics Point | B5: 1776835.4
A6: Arafat Traders | B6: 2418131
A7: Barisal Electronics | B7: 1668333.6
A8: Bismillah Traders | B8: 2445033.8
A9: Brothers Electronics | B9: 2318628.8
A10: Chattogram Battery Point | B10: 1650752.5
A11: City Battery Center | B11: 2797693.4
A12: Cumilla Traders | B12: 2041184.9
A13: Dhaka Battery Point | B13: 1943718.1
A14: Dhaka Hot Power Solution | B14: 3358912.1
A15: Digital Power BD | B15: 1765130.3
... A61: Win Battery Point | B61: 2375594.4
A62: (blank)
A63: Grand Total | B63: 1.2996518e+08

Sheet Sheet2
A3: Row Labels | B3: Sum of Sales_amount
A4: Barisal | B4: 8466866.1
A5: Bogura | B5: 8132112.2
A6: Chattogram | B6: 9886677.5
A7: Dhaka | B7: 9482589.4
A8: Habigonj | B8: 9929448.1
A9: Khulna | B9: 8379707.8
A10: Mymensingh | B10: 8235835.8
A11: Netrokuna | B11: 9399355.1
A12: Pabna | B12: 8288601.6
A13: Patuyakhali | B13: 9190099.6
A14: Rajabari | B14: 9787169.2
A15: Rajshahi | B15: 9903921.6
... A17: Sylhet | B17: 9506094.2
A18: (blank)
A19: Grand Total | B19: 1.2996518e+08

Sheet Pivot Table Products
A3: Row Labels | B3: Sum of Amount
A4: AGM Battery | B4: 2772511
A5: Automotive Battery | B5: 3268681
A6: Button Cell Battery | B6: 329388
A7: Coin Cell Battery | B7: 318619
A8: Deep Cycle Battery | B8: 3907635
A9: Drone LiPo Battery | B9: 4212780
A10: Electric Bike Battery | B10: 13218658
A11: Electric Scooter Battery | B11: 13030551
A12: Forklift Battery | B12: 8376778
A13: Gel Battery | B13: 3422367
A14: Hearing Aid Battery | B14: 369826
A15: Hybrid Vehicle Battery | B15: 14383602
... A33: UPS Backup Battery | B33: 3442060
A34: (blank)
A35: Grand Total | B35: 126776737

Sheet Pivot Table Executive
A3: Row Labels | B3: Sum of Amount
A4: Alamgir Hossen | B4: 9146844
A5: Eyad Hossian | B5: 9524715
A6: Jahid Hasan | B6: 8268661
A7: Karim Hasan | B7: 9683919
A8: Khairul Hasan | B8: 8942241
A9: Nayeem Islam | B9: 8147356
A10: Osman Faruk | B10: 9683389
A11: Rahim Ahmed | B11: 9245808
A12: Rakibul Hasan | B12: 11125954
A13: Ruhul Amin | B13: 8077999
A14: Sabbir Hossain | B14: 9263196
A15: Shahriar Joy | B15: 8034391
... A17: Tanvir Rahman | B17: 9673369
A18: (blank)
A19: Grand Total | B19: 126776737
